randan/__init__.py
randan/bivariate_association.py
randan/clustering.py
randan/comparison_of_central_tendency.py
randan/descriptive_statistics.py
randan/dimension_reduction.py
randan/regression.py
randan/tree.py
randan/utils.py
randan-0.3.1.2.dist-info/LICENSE
randan-0.3.1.2.dist-info/METADATA
randan-0.3.1.2.dist-info/WHEEL
randan-0.3.1.2.dist-info/top_level.txt
randan-0.3.1.2.dist-info/RECORD
