Metadata-Version: 2.1
Name: randan
Version: 0.3.1.2
Summary: A python package for gaining social and financial data and their analysis
Home-page: https://github.com/RandanCSS/randan
Download-URL: https://github.com/RandanCSS/randan/archive/refs/tags/v0.3.1.2.tar.gz
Author: Aleksei Rotmistrov, Svetlana Zhuchkova
Author-email: alexey.n.rotmistrov@gmail.com, lana_lob@mail.ru
License: MIT
Keywords: data,analysis,spss,youtube
Classifier: Programming Language :: Python :: 3
Classifier: License :: OSI Approved :: MIT License
Classifier: Operating System :: OS Independent
Requires-Python: >=3.6
License-File: LICENSE
Requires-Dist: factor_analyzer
Requires-Dist: google-api-python-client>=2.154.0
Requires-Dist: graphviz>=0.14
Requires-Dist: matplotlib>=3.1.1
Requires-Dist: numpy>=1.18.4
Requires-Dist: pandas>=1.0.3
Requires-Dist: pydot>=1.4.1
Requires-Dist: regex>=2024.9.11
Requires-Dist: scikit-learn>=0.23.1
Requires-Dist: statsmodels>=0.11.1
Requires-Dist: tqdm>=4.66.5
